audstream/__init__.py
audstream/voiceing.py
audstream-0.0.5.dist-info/LICENCE
audstream-0.0.5.dist-info/METADATA
audstream-0.0.5.dist-info/WHEEL
audstream-0.0.5.dist-info/top_level.txt
audstream-0.0.5.dist-info/RECORD
