Metadata-Version: 2.1
Name: audstream
Version: 0.0.5
Summary: A simple audio streaming library for Python.
Author: ryzmae (Ceeq9717)
Author-email: ryzmae <juwennagpal6@gmail.com>
Project-URL: Homepage, https://github.com/ceeq9717/audstream
Project-URL: Bug Tracker, https://github.com/ceeq9717/audstream/issues
Keywords: python,audio,stream,audio stream
Classifier: Programming Language :: Python :: 3
Classifier: License :: OSI Approved :: MIT License
Classifier: Operating System :: OS Independent
Requires-Python: >=3.7
License-File: LICENCE
Requires-Dist: wave
Requires-Dist: pyaudio
Requires-Dist: colorama
